dyspatch_client/__init__.py
dyspatch_client/api_client.py
dyspatch_client/configuration.py
dyspatch_client/exceptions.py
dyspatch_client/rest.py
dyspatch_client/api/__init__.py
dyspatch_client/api/drafts_api.py
dyspatch_client/api/localizations_api.py
dyspatch_client/api/templates_api.py
dyspatch_client/models/__init__.py
dyspatch_client/models/api_error.py
dyspatch_client/models/compiled_read.py
dyspatch_client/models/cursor.py
dyspatch_client/models/draft_meta_read.py
dyspatch_client/models/draft_read.py
dyspatch_client/models/drafts_read.py
dyspatch_client/models/inline_object.py
dyspatch_client/models/localization_key_read.py
dyspatch_client/models/localization_meta_read.py
dyspatch_client/models/localization_read.py
dyspatch_client/models/template_meta_read.py
dyspatch_client/models/template_read.py
dyspatch_client/models/templates_read.py
dyspatch_python-6.0.0.dist-info/METADATA
dyspatch_python-6.0.0.dist-info/WHEEL
dyspatch_python-6.0.0.dist-info/top_level.txt
dyspatch_python-6.0.0.dist-info/RECORD
