Metadata-Version: 2.1
Name: dyspatch-python
Version: 6.0.0
Summary: Dyspatch API
Home-page: UNKNOWN
Author: Dyspatch Support
Author-email: support@dyspatch.io
License: UNKNOWN
Keywords: OpenAPI,OpenAPI-Generator,Dyspatch API
Platform: UNKNOWN
Requires-Dist: urllib3 (>=1.15)
Requires-Dist: six (>=1.10)
Requires-Dist: certifi
Requires-Dist: python-dateutil
